magician_package/DE.py
magician_package/DE_ML.py
magician_package/DE_SVM.py
magician_package/FFT.py
magician_package/LDA.py
magician_package/LDADE.py
magician_package/ML.py
magician_package/Preprocess.py
magician_package/__init__.py
magician_package/demo.py
magician_package/featurization.py
magician_package/helpers.py
magician_package/ldavem.py
magician_package/read_pickle.py
magician_package/topics.py
magician_package/untitled1.py
magician_package/untuned.py
magician_package-0.3.38.dist-info/METADATA
magician_package-0.3.38.dist-info/RECORD
magician_package-0.3.38.dist-info/WHEEL
magician_package-0.3.38.dist-info/top_level.txt
