Metadata-Version: 2.1
Name: magician-package
Version: 0.3.38
Summary: A small example package for text mining application with hyper-parameter optimization on multiple learning to automatically find best model
Home-page: https://github.com/ai-se/magician_package
Author: RAISE_LAB
Author-email: smajumd3@ncsu.edu
License: UNKNOWN
Platform: UNKNOWN
Classifier: Programming Language :: Python :: 2.7
Classifier: License :: OSI Approved :: MIT License
Classifier: Operating System :: OS Independent
